piplog/__init__.py
piplog/piplog.py
piplog-0.0.1.dist-info/METADATA
piplog-0.0.1.dist-info/WHEEL
piplog-0.0.1.dist-info/top_level.txt
piplog-0.0.1.dist-info/RECORD
